[
    {
        "option2": "23",
        "option1": "51-86"
    },
    {
        "option2": "24",
        "option1": "69 - 104"
    },
    {
        "option2": "25",
        "option1": "86 - 123"
    },
    {
        "option2": "26",
        "option1": "103 - 141"
    },
    {
        "option2": "27",
        "option1": "120 - 159"
    },
    {
        "option2": "28",
        "option1": "138 - 178"
    },
    {
        "option2": "29",
        "option1": "155 - 196"
    },
    {
        "option2": "30",
        "option1": "172 - 215"
    },
    {
        "option2": "31",
        "option1": "207 - 250"
    },
    {
        "option2": "32",
        "option1": "241 - 286"
    },
    {
        "option2": "33",
        "option1": "276 - 322"
    },
    {
        "option2": "34",
        "option1": "310 - 357"
    },
    {
        "option2": "35",
        "option1": "345 - 393"
    },
    {
        "option2": "36",
        "option1": "379 - 428"
    },
    {
        "option2": "37",
        "option1": "414 - 464"
    },
    {
        "option2": "38",
        "option1": "448 - 500"
    },
    {
        "option2": "39",
        "option1": "500 - 553"
    },
    {
        "option2": "40",
        "option1": "552 - 606"
    },
    {
        "option2": "41",
        "option1": "603 - 658"
    },
    {
        "option2": "42",
        "option1": "655 - 711"
    }
]