[
    {
        "option2": "8",
        "option1": "1-43"
    },
    {
        "option2": "8.5",
        "option1": "1-51"
    },
    {
        "option2": "9",
        "option1": "1-60"
    },
    {
        "option2": "9.5",
        "option1": "1-69"
    },
    {
        "option2": "10",
        "option1": "1-77"
    },
    {
        "option2": "10.5",
        "option1": "1-86"
    },
    {
        "option2": "11",
        "option1": "1-95"
    },
    {
        "option2": "11.5",
        "option1": "1-103"
    },
    {
        "option2": "12",
        "option1": "1-116"
    },
    {
        "option2": "12",
        "option1": "1-129"
    },
    {
        "option2": "13",
        "option1": "1-142"
    },
    {
        "option2": "13",
        "option1": "1-155"
    },
    {
        "option2": "14",
        "option1": "1-168"
    },
    {
        "option2": "14",
        "option1": "1-181"
    },
    {
        "option2": "15",
        "option1": "1-194"
    },
    {
        "option2": "15",
        "option1": "1-207"
    },
    {
        "option2": "16",
        "option1": "1-228"
    },
    {
        "option2": "16",
        "option1": "1-250"
    },
    {
        "option2": "17",
        "option1": "1-272"
    },
    {
        "option2": "17",
        "option1": "1-293"
    }
]